odoo/addons/stock_quantity_history_location/README.rst
odoo/addons/stock_quantity_history_location/__init__.py
odoo/addons/stock_quantity_history_location/__manifest__.py
odoo/addons/stock_quantity_history_location/i18n/es.po
odoo/addons/stock_quantity_history_location/i18n/it.po
odoo/addons/stock_quantity_history_location/i18n/ja.po
odoo/addons/stock_quantity_history_location/i18n/pt_BR.po
odoo/addons/stock_quantity_history_location/i18n/ro.po
odoo/addons/stock_quantity_history_location/i18n/stock_quantity_history_location.pot
odoo/addons/stock_quantity_history_location/readme/CONTRIBUTORS.md
odoo/addons/stock_quantity_history_location/readme/DESCRIPTION.md
odoo/addons/stock_quantity_history_location/readme/USAGE.md
odoo/addons/stock_quantity_history_location/static/description/icon.png
odoo/addons/stock_quantity_history_location/static/description/index.html
odoo/addons/stock_quantity_history_location/tests/__init__.py
odoo/addons/stock_quantity_history_location/tests/common.py
odoo/addons/stock_quantity_history_location/tests/test_stock_quantity_history_location.py
odoo/addons/stock_quantity_history_location/views/product_views.xml
odoo/addons/stock_quantity_history_location/wizards/__init__.py
odoo/addons/stock_quantity_history_location/wizards/stock_quantity_history.py
odoo/addons/stock_quantity_history_location/wizards/stock_quantity_history.xml
odoo_addon_stock_quantity_history_location-18.0.1.0.0.4.dist-info/METADATA
odoo_addon_stock_quantity_history_location-18.0.1.0.0.4.dist-info/WHEEL
odoo_addon_stock_quantity_history_location-18.0.1.0.0.4.dist-info/top_level.txt
odoo_addon_stock_quantity_history_location-18.0.1.0.0.4.dist-info/RECORD
